LingzuWenkuBuquanFix1/README.md
LingzuWenkuBuquanFix1/__init__.py
LingzuWenkuBuquanFix1/__main__.py
LingzuWenkuBuquanFix1/file.epub
LingzuWenkuBuquanFix1/index.html
LingzuWenkuBuquanFix1/css/__init__.py
LingzuWenkuBuquanFix1/css/annotations.css
LingzuWenkuBuquanFix1/css/main.css
LingzuWenkuBuquanFix1/css/normalize.css
LingzuWenkuBuquanFix1/css/popup.css
LingzuWenkuBuquanFix1/font/__init__.py
LingzuWenkuBuquanFix1/font/fontello.eot
LingzuWenkuBuquanFix1/font/fontello.svg
LingzuWenkuBuquanFix1/font/fontello.ttf
LingzuWenkuBuquanFix1/font/fontello.woff
LingzuWenkuBuquanFix1/img/__init__.py
LingzuWenkuBuquanFix1/img/annotator-glyph-sprite.png
LingzuWenkuBuquanFix1/img/annotator-icon-sprite.png
LingzuWenkuBuquanFix1/img/apple-touch-icon.png
LingzuWenkuBuquanFix1/img/cancelfullscreen.png
LingzuWenkuBuquanFix1/img/close.png
LingzuWenkuBuquanFix1/img/fullscreen.png
LingzuWenkuBuquanFix1/img/loader.gif
LingzuWenkuBuquanFix1/img/menu-icon.png
LingzuWenkuBuquanFix1/img/save.png
LingzuWenkuBuquanFix1/img/saved.png
LingzuWenkuBuquanFix1/img/settings-s.png
LingzuWenkuBuquanFix1/img/settings.png
LingzuWenkuBuquanFix1/img/star.png
LingzuWenkuBuquanFix1/js/__init__.py
LingzuWenkuBuquanFix1/js/epub.js
LingzuWenkuBuquanFix1/js/epub.min.js
LingzuWenkuBuquanFix1/js/epub.min.map
LingzuWenkuBuquanFix1/js/hooks.min.js
LingzuWenkuBuquanFix1/js/hooks.min.map
LingzuWenkuBuquanFix1/js/reader.js
LingzuWenkuBuquanFix1/js/reader.js.map
LingzuWenkuBuquanFix1/js/reader.min.js
LingzuWenkuBuquanFix1/js/reader.min.map
LingzuWenkuBuquanFix1/js/hooks/__init__.py
LingzuWenkuBuquanFix1/js/hooks/extensions/__init__.py
LingzuWenkuBuquanFix1/js/hooks/extensions/highlight.js
LingzuWenkuBuquanFix1/js/libs/__init__.py
LingzuWenkuBuquanFix1/js/libs/jquery.min.js
LingzuWenkuBuquanFix1/js/libs/localforage.min.js
LingzuWenkuBuquanFix1/js/libs/screenfull.js
LingzuWenkuBuquanFix1/js/libs/screenfull.min.js
LingzuWenkuBuquanFix1/js/libs/zip.min.js
LingzuWenkuBuquanFix1/js/plugins/__init__.py
lingzu_wenku_buquan_fix1-2025.3.24.1.dist-info/METADATA
lingzu_wenku_buquan_fix1-2025.3.24.1.dist-info/WHEEL
lingzu_wenku_buquan_fix1-2025.3.24.1.dist-info/entry_points.txt
lingzu_wenku_buquan_fix1-2025.3.24.1.dist-info/top_level.txt
lingzu_wenku_buquan_fix1-2025.3.24.1.dist-info/RECORD
